[
  {
    "model": "book.book",
    "pk": 1,
    "fields": {
      "title": "Book A1",
      "author": "Author 1",
      "genre": "Adventure",
      "updated_at": "2024-07-21T12:00:00Z",
      "created_at": "2024-07-21T12:00:00Z"
    }
  },
  {
    "model": "book.book",
    "pk": 2,
    "fields": {
      "title": "Book A2",
      "author": "Author 1",
      "genre": "Mystery",
      "updated_at": "2024-07-21T12:00:00Z",
      "created_at": "2024-07-21T12:00:00Z"
    }
  },
  {
    "model": "book.book",
    "pk": 3,
    "fields": {
      "title": "Book A3",
      "author": "Author 1",
      "genre": "Science Fiction",
      "updated_at": "2024-07-21T12:00:00Z",
      "created_at": "2024-07-21T12:00:00Z"
    }
  },
  {
    "model": "book.book",
    "pk": 4,
    "fields": {
      "title": "Book B1",
      "author": "Author 2",
      "genre": "History",
      "updated_at": "2024-07-21T12:00:00Z",
      "created_at": "2024-07-21T12:00:00Z"
    }
  },
  {
    "model": "book.book",
    "pk": 5,
    "fields": {
      "title": "Book B2",
      "author": "Author 2",
      "genre": "Romance",
      "updated_at": "2024-07-21T12:00:00Z",
      "created_at": "2024-07-21T12:00:00Z"
    }
  },
  {
    "model": "book.book",
    "pk": 6,
    "fields": {
      "title": "Book B3",
      "author": "Author 2",
      "genre": "Science",
      "updated_at": "2024-07-21T12:00:00Z",
      "created_at": "2024-07-21T12:00:00Z"
    }
  },
  {
    "model": "book.book",
    "pk": 7,
    "fields": {
      "title": "Book C1",
      "author": "Author 3",
      "genre": "Cooking",
      "updated_at": "2024-07-21T12:00:00Z",
      "created_at": "2024-07-21T12:00:00Z"
    }
  },
  {
    "model": "book.book",
    "pk": 8,
    "fields": {
      "title": "Book C2",
      "author": "Author 3",
      "genre": "Gardening",
      "updated_at": "2024-07-21T12:00:00Z",
      "created_at": "2024-07-21T12:00:00Z"
    }
  },
  {
    "model": "book.book",
    "pk": 9,
    "fields": {
      "title": "Book C3",
      "author": "Author 3",
      "genre": "Travel",
      "updated_at": "2024-07-21T12:00:00Z",
      "created_at": "2024-07-21T12:00:00Z"
    }
  },
  {
    "model": "book.book",
    "pk": 10,
    "fields": {
      "title": "Book D1",
      "author": "Author 4",
      "genre": "Adventure",
      "updated_at": "2024-07-21T12:00:00Z",
      "created_at": "2024-07-21T12:00:00Z"
    }
  },
  {
    "model": "book.book",
    "pk": 11,
    "fields": {
      "title": "Book D2",
      "author": "Author 4",
      "genre": "Adventure",
      "updated_at": "2024-07-21T12:00:00Z",
      "created_at": "2024-07-21T12:00:00Z"
    }
  },
  {
    "model": "book.book",
    "pk": 12,
    "fields": {
      "title": "Book D3",
      "author": "Author 4",
      "genre": "Adventure",
      "updated_at": "2024-07-21T12:00:00Z",
      "created_at": "2024-07-21T12:00:00Z"
    }
  },
  {
    "model": "book.book",
    "pk": 13,
    "fields": {
      "title": "Book E1",
      "author": "Author 5",
      "genre": "Mystery",
      "updated_at": "2024-07-21T12:00:00Z",
      "created_at": "2024-07-21T12:00:00Z"
    }
  },
  {
    "model": "book.book",
    "pk": 14,
    "fields": {
      "title": "Book E2",
      "author": "Author 5",
      "genre": "Mystery",
      "updated_at": "2024-07-21T12:00:00Z",
      "created_at": "2024-07-21T12:00:00Z"
    }
  },
  {
    "model": "book.book",
    "pk": 15,
    "fields": {
      "title": "Book E3",
      "author": "Author 5",
      "genre": "Mystery",
      "updated_at": "2024-07-21T12:00:00Z",
      "created_at": "2024-07-21T12:00:00Z"
    }
  },
  {
    "model": "book.book",
    "pk": 16,
    "fields": {
      "title": "Book F1",
      "author": "Author 6",
      "genre": "Science",
      "updated_at": "2024-07-21T12:00:00Z",
      "created_at": "2024-07-21T12:00:00Z"
    }
  },
  {
    "model": "book.book",
    "pk": 17,
    "fields": {
      "title": "Book F2",
      "author": "Author 7",
      "genre": "History",
      "updated_at": "2024-07-21T12:00:00Z",
      "created_at": "2024-07-21T12:00:00Z"
    }
  },
  {
    "model": "book.book",
    "pk": 18,
    "fields": {
      "title": "Book F3",
      "author": "Author 8",
      "genre": "Romance",
      "updated_at": "2024-07-21T12:00:00Z",
      "created_at": "2024-07-21T12:00:00Z"
    }
  },
  {
    "model": "book.book",
    "pk": 19,
    "fields": {
      "title": "Book F4",
      "author": "Author 9",
      "genre": "Science Fiction",
      "updated_at": "2024-07-21T12:00:00Z",
      "created_at": "2024-07-21T12:00:00Z"
    }
  },
  {
    "model": "book.book",
    "pk": 20,
    "fields": {
      "title": "Book F5",
      "author": "Author 10",
      "genre": "Cooking",
      "updated_at": "2024-07-21T12:00:00Z",
      "created_at": "2024-07-21T12:00:00Z"
    }
  },
  {
    "model": "book.book",
    "pk": 21,
    "fields": {
      "title": "Book F6",
      "author": "Author 11",
      "genre": "Gardening",
      "updated_at": "2024-07-21T12:00:00Z",
      "created_at": "2024-07-21T12:00:00Z"
    }
  },
  {
    "model": "book.book",
    "pk": 22,
    "fields": {
      "title": "Book F7",
      "author": "Author 12",
      "genre": "Travel",
      "updated_at": "2024-07-21T12:00:00Z",
      "created_at": "2024-07-21T12:00:00Z"
    }
  },
  {
    "model": "book.book",
    "pk": 23,
    "fields": {
      "title": "Book F8",
      "author": "Author 13",
      "genre": "Education",
      "updated_at": "2024-07-21T12:00:00Z",
      "created_at": "2024-07-21T12:00:00Z"
    }
  },
  {
    "model": "book.book",
    "pk": 24,
    "fields": {
      "title": "Book F9",
      "author": "Author 14",
      "genre": "Horror",
      "updated_at": "2024-07-21T12:00:00Z",
      "created_at": "2024-07-21T12:00:00Z"
    }
  },
  {
    "model": "book.book",
    "pk": 25,
    "fields": {
      "title": "Book F10",
      "author": "Author 15",
      "genre": "Adventure",
      "updated_at": "2024-07-21T12:00:00Z",
      "created_at": "2024-07-21T12:00:00Z"
    }
  },
  {
    "model": "book.book",
    "pk": 26,
    "fields": {
      "title": "Book F11",
      "author": "Author 16",
      "genre": "Mystery",
      "updated_at": "2024-07-21T12:00:00Z",
      "created_at": "2024-07-21T12:00:00Z"
    }
  },
  {
    "model": "book.book",
    "pk": 27,
    "fields": {
      "title": "Book F12",
      "author": "Author 17",
      "genre": "Science",
      "updated_at": "2024-07-21T12:00:00Z",
      "created_at": "2024-07-21T12:00:00Z"
    }
  },
  {
    "model": "book.book",
    "pk": 28,
    "fields": {
      "title": "Book F13",
      "author": "Author 18",
      "genre": "History",
      "updated_at": "2024-07-21T12:00:00Z",
      "created_at": "2024-07-21T12:00:00Z"
    }
  },
  {
    "model": "book.book",
    "pk": 29,
    "fields": {
      "title": "Book F14",
      "author": "Author 19",
      "genre": "Romance",
      "updated_at": "2024-07-21T12:00:00Z",
      "created_at": "2024-07-21T12:00:00Z"
    }
  },
  {
    "model": "book.book",
    "pk": 30,
    "fields": {
      "title": "Book F15",
      "author": "Author 20",
      "genre": "Science Fiction",
      "updated_at": "2024-07-21T12:00:00Z",
      "created_at": "2024-07-21T12:00:00Z"
    }
  },
  {
    "model": "book.book",
    "pk": 31,
    "fields": {
      "title": "Book F16",
      "author": "Author 21",
      "genre": "Cooking",
      "updated_at": "2024-07-21T12:00:00Z",
      "created_at": "2024-07-21T12:00:00Z"
    }
  },
  {
    "model": "book.book",
    "pk": 32,
    "fields": {
      "title": "Book F17",
      "author": "Author 22",
      "genre": "Gardening",
      "updated_at": "2024-07-21T12:00:00Z",
      "created_at": "2024-07-21T12:00:00Z"
    }
  },
  {
    "model": "book.book",
    "pk": 33,
    "fields": {
      "title": "Book F18",
      "author": "Author 23",
      "genre": "Travel",
      "updated_at": "2024-07-21T12:00:00Z",
      "created_at": "2024-07-21T12:00:00Z"
    }
  },
  {
    "model": "book.book",
    "pk": 34,
    "fields": {
      "title": "Book F19",
      "author": "Author 24",
      "genre": "Education",
      "updated_at": "2024-07-21T12:00:00Z",
      "created_at": "2024-07-21T12:00:00Z"
    }
  },
  {
    "model": "book.book",
    "pk": 35,
    "fields": {
      "title": "Book F20",
      "author": "Author 25",
      "genre": "Horror",
      "updated_at": "2024-07-21T12:00:00Z",
      "created_at": "2024-07-21T12:00:00Z"
    }
  },
  {
    "model": "book.book",
    "pk": 36,
    "fields": {
      "title": "Book F21",
      "author": "Author 6",
      "genre": "Romance",
      "updated_at": "2024-07-21T12:00:00Z",
      "created_at": "2024-07-21T12:00:00Z"
    }
  },
  {
    "model": "book.book",
    "pk": 37,
    "fields": {
      "title": "Book F22",
      "author": "Author 7",
      "genre": "Adventure",
      "updated_at": "2024-07-21T12:00:00Z",
      "created_at": "2024-07-21T12:00:00Z"
    }
  },
  {
    "model": "book.book",
    "pk": 38,
    "fields": {
      "title": "Book F23",
      "author": "Author 8",
      "genre": "Mystery",
      "updated_at": "2024-07-21T12:00:00Z",
      "created_at": "2024-07-21T12:00:00Z"
    }
  },
  {
    "model": "book.book",
    "pk": 39,
    "fields": {
      "title": "Book F24",
      "author": "Author 9",
      "genre": "Science",
      "updated_at": "2024-07-21T12:00:00Z",
      "created_at": "2024-07-21T12:00:00Z"
    }
  },
  {
    "model": "book.book",
    "pk": 40,
    "fields": {
      "title": "Book F25",
      "author": "Author 10",
      "genre": "History",
      "updated_at": "2024-07-21T12:00:00Z",
      "created_at": "2024-07-21T12:00:00Z"
    }
  },
  {
    "model": "book.book",
    "pk": 41,
    "fields": {
      "title": "Book F26",
      "author": "Author 11",
      "genre": "Romance",
      "updated_at": "2024-07-21T12:00:00Z",
      "created_at": "2024-07-21T12:00:00Z"
    }
  },
  {
    "model": "book.book",
    "pk": 42,
    "fields": {
      "title": "Book F27",
      "author": "Author 12",
      "genre": "Science Fiction",
      "updated_at": "2024-07-21T12:00:00Z",
      "created_at": "2024-07-21T12:00:00Z"
    }
  },
  {
    "model": "book.book",
    "pk": 43,
    "fields": {
      "title": "Book F28",
      "author": "Author 13",
      "genre": "Cooking",
      "updated_at": "2024-07-21T12:00:00Z",
      "created_at": "2024-07-21T12:00:00Z"
    }
  },
  {
    "model": "book.book",
    "pk": 44,
    "fields": {
      "title": "Book F29",
      "author": "Author 14",
      "genre": "Gardening",
      "updated_at": "2024-07-21T12:00:00Z",
      "created_at": "2024-07-21T12:00:00Z"
    }
  },
  {
    "model": "book.book",
    "pk": 45,
    "fields": {
      "title": "Book F30",
      "author": "Author 15",
      "genre": "Travel",
      "updated_at": "2024-07-21T12:00:00Z",
      "created_at": "2024-07-21T12:00:00Z"
    }
  },
  {
    "model": "book.book",
    "pk": 46,
    "fields": {
      "title": "Book F31",
      "author": "Author 16",
      "genre": "Education",
      "updated_at": "2024-07-21T12:00:00Z",
      "created_at": "2024-07-21T12:00:00Z"
    }
  },
  {
    "model": "book.book",
    "pk": 47,
    "fields": {
      "title": "Book F32",
      "author": "Author 17",
      "genre": "Horror",
      "updated_at": "2024-07-21T12:00:00Z",
      "created_at": "2024-07-21T12:00:00Z"
    }
  },
  {
    "model": "book.book",
    "pk": 48,
    "fields": {
      "title": "Book F33",
      "author": "Author 18",
      "genre": "Adventure",
      "updated_at": "2024-07-21T12:00:00Z",
      "created_at": "2024-07-21T12:00:00Z"
    }
  },
  {
    "model": "book.book",
    "pk": 49,
    "fields": {
      "title": "Book F34",
      "author": "Author 19",
      "genre": "Mystery",
      "updated_at": "2024-07-21T12:00:00Z",
      "created_at": "2024-07-21T12:00:00Z"
    }
  },
  {
    "model": "book.book",
    "pk": 50,
    "fields": {
      "title": "Book F35",
      "author": "Author 20",
      "genre": "Science",
      "updated_at": "2024-07-21T12:00:00Z",
      "created_at": "2024-07-21T12:00:00Z"
    }
  },
  {
    "model": "book.book",
    "pk": 51,
    "fields": {
      "title": "Book F36",
      "author": "Author 21",
      "genre": "History",
      "updated_at": "2024-07-21T12:00:00Z",
      "created_at": "2024-07-21T12:00:00Z"
    }
  },
  {
    "model": "book.book",
    "pk": 52,
    "fields": {
      "title": "Book F37",
      "author": "Author 22",
      "genre": "Romance",
      "updated_at": "2024-07-21T12:00:00Z",
      "created_at": "2024-07-21T12:00:00Z"
    }
  },
  {
    "model": "book.book",
    "pk": 53,
    "fields": {
      "title": "Book F38",
      "author": "Author 23",
      "genre": "Science Fiction",
      "updated_at": "2024-07-21T12:00:00Z",
      "created_at": "2024-07-21T12:00:00Z"
    }
  },
  {
    "model": "book.book",
    "pk": 54,
    "fields": {
      "title": "Book F39",
      "author": "Author 24",
      "genre": "Cooking",
      "updated_at": "2024-07-21T12:00:00Z",
      "created_at": "2024-07-21T12:00:00Z"
    }
  },
  {
    "model": "book.book",
    "pk": 55,
    "fields": {
      "title": "Book F40",
      "author": "Author 25",
      "genre": "Gardening",
      "updated_at": "2024-07-21T12:00:00Z",
      "created_at": "2024-07-21T12:00:00Z"
    }
  },
  {
    "model": "book.book",
    "pk": 56,
    "fields": {
      "title": "Book F41",
      "author": "Author 6",
      "genre": "Travel",
      "updated_at": "2024-07-21T12:00:00Z",
      "created_at": "2024-07-21T12:00:00Z"
    }
  },
  {
    "model": "book.book",
    "pk": 57,
    "fields": {
      "title": "Book F42",
      "author": "Author 7",
      "genre": "Education",
      "updated_at": "2024-07-21T12:00:00Z",
      "created_at": "2024-07-21T12:00:00Z"
    }
  },
  {
    "model": "book.book",
    "pk": 58,
    "fields": {
      "title": "Book F43",
      "author": "Author 8",
      "genre": "Horror",
      "updated_at": "2024-07-21T12:00:00Z",
      "created_at": "2024-07-21T12:00:00Z"
    }
  },
  {
    "model": "book.book",
    "pk": 59,
    "fields": {
      "title": "Book F44",
      "author": "Author 9",
      "genre": "Adventure",
      "updated_at": "2024-07-21T12:00:00Z",
      "created_at": "2024-07-21T12:00:00Z"
    }
  },
  {
    "model": "book.book",
    "pk": 60,
    "fields": {
      "title": "Book F45",
      "author": "Author 10",
      "genre": "Mystery",
      "updated_at": "2024-07-21T12:00:00Z",
      "created_at": "2024-07-21T12:00:00Z"
    }
  },
  {
    "model": "book.book",
    "pk": 61,
    "fields": {
      "title": "Book F46",
      "author": "Author 11",
      "genre": "Science",
      "updated_at": "2024-07-21T12:00:00Z",
      "created_at": "2024-07-21T12:00:00Z"
    }
  },
  {
    "model": "book.book",
    "pk": 62,
    "fields": {
      "title": "Book F47",
      "author": "Author 12",
      "genre": "History",
      "updated_at": "2024-07-21T12:00:00Z",
      "created_at": "2024-07-21T12:00:00Z"
    }
  },
  {
    "model": "book.book",
    "pk": 63,
    "fields": {
      "title": "Book F48",
      "author": "Author 13",
      "genre": "Romance",
      "updated_at": "2024-07-21T12:00:00Z",
      "created_at": "2024-07-21T12:00:00Z"
    }
  },
  {
    "model": "book.book",
    "pk": 64,
    "fields": {
      "title": "Book F49",
      "author": "Author 14",
      "genre": "Science Fiction",
      "updated_at": "2024-07-21T12:00:00Z",
      "created_at": "2024-07-21T12:00:00Z"
    }
  },
  {
    "model": "book.book",
    "pk": 65,
    "fields": {
      "title": "Book F50",
      "author": "Author 15",
      "genre": "Cooking",
      "updated_at": "2024-07-21T12:00:00Z",
      "created_at": "2024-07-21T12:00:00Z"
    }
  }
]
